<?xml version="1.0" encoding="utf-8" ?>
<dwsync>
<file name="ColabReg-webfont.eot" server="webdata.cs.ucy.ac.cy//WebData/projects/smartLib/" local="129169359820000000" remote="129881640970000000" Dst="2" />
<file name="ColabReg-webfont.woff" server="webdata.cs.ucy.ac.cy//WebData/projects/smartLib/" local="129169359820000000" remote="129881640980000000" Dst="2" />
<file name="ColabReg-webfont.ttf" server="webdata.cs.ucy.ac.cy//WebData/projects/smartLib/" local="129169359820000000" remote="129881640990000000" Dst="2" />
<file name="HighlandGothicLightFLF-webfont.eot" server="webdata.cs.ucy.ac.cy//WebData/projects/smartLib/" local="129169412140000000" remote="129881641000000000" Dst="2" />
<file name="HighlandGothicLightFLF-webfont.woff" server="webdata.cs.ucy.ac.cy//WebData/projects/smartLib/" local="129169412140000000" remote="129881641010000000" Dst="2" />
<file name="HighlandGothicLightFLF-webfont.ttf" server="webdata.cs.ucy.ac.cy//WebData/projects/smartLib/" local="129169412140000000" remote="129881641010000000" Dst="2" />
<file name=".DS_Store" server="webdata.cs.ucy.ac.cy//WebData/projects/smartLib/" local="129199547520000000" remote="129881650940000000" Dst="2" />
<file name="ColabReg-webfont.svg" server="webdata.cs.ucy.ac.cy//WebData/projects/smartLib/" local="129169359820000000" remote="129881650950000000" Dst="2" />
<file name="HighlandGothicLightFLF-webfont.svg" server="webdata.cs.ucy.ac.cy//WebData/projects/smartLib/" local="129169412140000000" remote="129881650980000000" Dst="2" />
</dwsync>